{"name":"Rain","tracks":[{"kind":"youtube#searchResult","etag":"\"p4VTdlkQv3HQeTEaXgvLePAydmU/Suq7zOsit4i484HetF5uuB_qEgQ\"","id":{"kind":"youtube#video","videoId":"JlIj6BxUS6E"},"snippet":{"publishedAt":"2011-07-06T15:22:03.000Z","channelId":"UC7eaRqtonpyiYw0Pns0Au_g","title":"R.E.M. - I&#39;ll Take The Rain (Official Music Video)","description":"\"I'll Take The Rain\" from R.E.M.'s 2001 album, \"Reveal\" Buy the album: https://rem.lnk.to/RevealYD To learn more, visit http://www.remhq.com.","thumbnails":{"default":{"url":"https://i.ytimg.com/vi/JlIj6BxUS6E/default.jpg","width":120,"height":90},"medium":{"url":"https://i.ytimg.com/vi/JlIj6BxUS6E/mqdefault.jpg","width":320,"height":180},"high":{"url":"https://i.ytimg.com/vi/JlIj6BxUS6E/hqdefault.jpg","width":480,"height":360}},"channelTitle":"remhq","liveBroadcastContent":"none"},"_playlist":"xx71wje4akb","_playlistItem":"uu5jh6y4gwp"},{"kind":"youtube#searchResult","etag":"\"p4VTdlkQv3HQeTEaXgvLePAydmU/5AXKQqS2h7UQNmdXG7Js3E42-hU\"","id":{"kind":"youtube#video","videoId":"KxKANJdEHQg"},"snippet":{"publishedAt":"2014-04-03T11:56:34.000Z","channelId":"UC4GpcdFxs6SG5ABPrrNA6GA","title":"עברי לידר - גשם אחרון // Ivri Lider - Last Rain","description":"לרכישה Purchse http://ivrilider.bandcamp.com/album/ivri-lider-the-new-people-haanashim-hachadashim iTunes: ...","thumbnails":{"default":{"url":"https://i.ytimg.com/vi/KxKANJdEHQg/default.jpg","width":120,"height":90},"medium":{"url":"https://i.ytimg.com/vi/KxKANJdEHQg/mqdefault.jpg","width":320,"height":180},"high":{"url":"https://i.ytimg.com/vi/KxKANJdEHQg/hqdefault.jpg","width":480,"height":360}},"channelTitle":"Ivri Lider","liveBroadcastContent":"none"},"_playlist":"xx71wje4akb","_playlistItem":"ppxe5tgof8"},{"kind":"youtube#searchResult","etag":"\"p4VTdlkQv3HQeTEaXgvLePAydmU/yQDoWB-HFoTmFI6EzP5eTLq83c0\"","id":{"kind":"youtube#video","videoId":"UN6Sw3Rh6ug"},"snippet":{"publishedAt":"2010-11-08T08:18:03.000Z","channelId":"UCrlx-kNohG7mJbfPYbvo-WQ","title":"I Wish it Would Rain Down ( with Lyrics )  - Phil Collins","description":"Just Love this Beautiful Song ...Big thanks to everyone for all the appreciation, wonderful comments and Blessings. Thanks for watching the video ...God Bless ...","thumbnails":{"default":{"url":"https://i.ytimg.com/vi/UN6Sw3Rh6ug/default.jpg","width":120,"height":90},"medium":{"url":"https://i.ytimg.com/vi/UN6Sw3Rh6ug/mqdefault.jpg","width":320,"height":180},"high":{"url":"https://i.ytimg.com/vi/UN6Sw3Rh6ug/hqdefault.jpg","width":480,"height":360}},"channelTitle":"TrueHeartGuy85","liveBroadcastContent":"none"},"_playlist":"xx71wje4akb","_playlistItem":"0nbrzsaqq6z"},{"kind":"youtube#searchResult","etag":"\"p4VTdlkQv3HQeTEaXgvLePAydmU/ZmOfOByLRQde_P0ovFsu2OJ8-qQ\"","id":{"kind":"youtube#video","videoId":"WvzitKFHh-w"},"snippet":{"publishedAt":"2011-04-17T08:11:30.000Z","channelId":"UCHaf6dsn_DHwEsfzHYPnMXw","title":"מאיר בנאי - גשם (אודיו)","description":"עמוד הפייסבוק הרשמי: http://www.facebook.com/Meir.Banai ▻ אתר אינטרנט: https://MeirBanai.confia.co.il ▻ iTunes - רכישת שירים: https://itunes.apple.com/i...","thumbnails":{"default":{"url":"https://i.ytimg.com/vi/WvzitKFHh-w/default.jpg","width":120,"height":90},"medium":{"url":"https://i.ytimg.com/vi/WvzitKFHh-w/mqdefault.jpg","width":320,"height":180},"high":{"url":"https://i.ytimg.com/vi/WvzitKFHh-w/hqdefault.jpg","width":480,"height":360}},"channelTitle":"מאיר בנאי – הערוץ הרשמי","liveBroadcastContent":"none"},"_playlist":"xx71wje4akb","_playlistItem":"gqcq730snz9"},{"kind":"youtube#searchResult","etag":"\"p4VTdlkQv3HQeTEaXgvLePAydmU/gaRcEqgkwi0YVtnKBSBQdbjluOA\"","id":{"kind":"youtube#video","videoId":"gEnCxGh8kBg"},"snippet":{"publishedAt":"2009-01-28T15:49:05.000Z","channelId":"UCU5A0SbbQMx5FbHOx3-AiSQ","title":"Raining In Baltimore - Counting Crows","description":"Raining In Baltimore - Counting Crows... Amazing... :)","thumbnails":{"default":{"url":"https://i.ytimg.com/vi/gEnCxGh8kBg/default.jpg","width":120,"height":90},"medium":{"url":"https://i.ytimg.com/vi/gEnCxGh8kBg/mqdefault.jpg","width":320,"height":180},"high":{"url":"https://i.ytimg.com/vi/gEnCxGh8kBg/hqdefault.jpg","width":480,"height":360}},"channelTitle":"NDS Group","liveBroadcastContent":"none"},"_playlist":"xx71wje4akb","_playlistItem":"gpoyhu6r2cs"},{"kind":"youtube#searchResult","etag":"\"p4VTdlkQv3HQeTEaXgvLePAydmU/9NmvykGLpNGqgkpGz6u7qHHCXro\"","id":{"kind":"youtube#video","videoId":"4Joqgqa4brw"},"snippet":{"publishedAt":"2011-01-26T15:42:06.000Z","channelId":"UCQHzG2gtNfXp4yo6_I46eCw","title":"שלמה ארצי- טלפני טלפני","description":"טלפני טלפני מתוך חום יולי אוגוסט- 1988.","thumbnails":{"default":{"url":"https://i.ytimg.com/vi/4Joqgqa4brw/default.jpg","width":120,"height":90},"medium":{"url":"https://i.ytimg.com/vi/4Joqgqa4brw/mqdefault.jpg","width":320,"height":180},"high":{"url":"https://i.ytimg.com/vi/4Joqgqa4brw/hqdefault.jpg","width":480,"height":360}},"channelTitle":"ShlomoArtziOfficial","liveBroadcastContent":"none"},"_playlist":"xx71wje4akb","_playlistItem":"jusjjk0jlzf"},{"kind":"youtube#searchResult","etag":"\"p4VTdlkQv3HQeTEaXgvLePAydmU/NNaahVXnXOPAJR9vGZTR-F1LCFs\"","id":{"kind":"youtube#video","videoId":"UIVNwqTXwT0"},"snippet":{"publishedAt":"2011-04-06T12:35:38.000Z","channelId":"UCk9of4cjP9oHysTXYGkCN_w","title":"נורית גלרון - אתה פה חסר לי","description":"לרכישת האלבום החדש \"שירים באמצע הלילה\" שיצא בהוצאה מחודשת : http://tiny.cc/ShirimCD בשנות התשעים החלה גלרון לעבוד עם...","thumbnails":{"default":{"url":"https://i.ytimg.com/vi/UIVNwqTXwT0/default.jpg","width":120,"height":90},"medium":{"url":"https://i.ytimg.com/vi/UIVNwqTXwT0/mqdefault.jpg","width":320,"height":180},"high":{"url":"https://i.ytimg.com/vi/UIVNwqTXwT0/hqdefault.jpg","width":480,"height":360}},"channelTitle":"מוזיקה ישראלית","liveBroadcastContent":"none"},"_playlist":"xx71wje4akb","_playlistItem":"qb48ogzdkw"},{"kind":"youtube#searchResult","etag":"\"p4VTdlkQv3HQeTEaXgvLePAydmU/PHe7FFnO_onDOruzWcRpIDwV0zg\"","id":{"kind":"youtube#video","videoId":"qBrHhKC8lAI"},"snippet":{"publishedAt":"2011-05-18T06:40:57.000Z","channelId":"UCQHzG2gtNfXp4yo6_I46eCw","title":"שלמה ארצי - סיפור רומנטי","description":"שניים 1995 שתי רגלייך התנועעו בקצב המטורף, אדם מרגיש כשהוא הולך להתרסק, שאלתי שם כשלא ראו, מי את, מאיפה באת?...","thumbnails":{"default":{"url":"https://i.ytimg.com/vi/qBrHhKC8lAI/default.jpg","width":120,"height":90},"medium":{"url":"https://i.ytimg.com/vi/qBrHhKC8lAI/mqdefault.jpg","width":320,"height":180},"high":{"url":"https://i.ytimg.com/vi/qBrHhKC8lAI/hqdefault.jpg","width":480,"height":360}},"channelTitle":"ShlomoArtziOfficial","liveBroadcastContent":"none"},"_playlist":"xx71wje4akb","_playlistItem":"mgugg1wu97j"},{"kind":"youtube#searchResult","etag":"\"p4VTdlkQv3HQeTEaXgvLePAydmU/wmveER5tY6AzKNAV5PlY2V9_1I8\"","id":{"kind":"youtube#video","videoId":"msWi0c4tHV8"},"snippet":{"publishedAt":"2009-07-20T01:30:40.000Z","channelId":"UC1_8rTKqHNZC4JfpMHKY93g","title":"R.E.M. - So. Central Rain","description":"Music video by R.E.M. performing So. Central Rain.","thumbnails":{"default":{"url":"https://i.ytimg.com/vi/msWi0c4tHV8/default.jpg","width":120,"height":90},"medium":{"url":"https://i.ytimg.com/vi/msWi0c4tHV8/mqdefault.jpg","width":320,"height":180},"high":{"url":"https://i.ytimg.com/vi/msWi0c4tHV8/hqdefault.jpg","width":480,"height":360}},"channelTitle":"REMVEVO","liveBroadcastContent":"none"},"_playlist":"xx71wje4akb","_playlistItem":"7v4g9jc9nlf"},{"kind":"youtube#searchResult","etag":"\"p4VTdlkQv3HQeTEaXgvLePAydmU/rAC2megvxDDpo1mCTRf39bt2UiI\"","id":{"kind":"youtube#video","videoId":"fHiGbolFFGw"},"snippet":{"publishedAt":"2015-01-23T10:18:00.000Z","channelId":"UCq19-LqvG35A-30oyAiPiqA","title":"Radiohead - Paranoid Android","description":"Official Promo Video for Radiohead's \"Paranoid Android\".","thumbnails":{"default":{"url":"https://i.ytimg.com/vi/fHiGbolFFGw/default.jpg","width":120,"height":90},"medium":{"url":"https://i.ytimg.com/vi/fHiGbolFFGw/mqdefault.jpg","width":320,"height":180},"high":{"url":"https://i.ytimg.com/vi/fHiGbolFFGw/hqdefault.jpg","width":480,"height":360}},"channelTitle":"Radiohead","liveBroadcastContent":"none"},"_playlist":"xx71wje4akb","_playlistItem":"jbjxsq4v4x"},{"kind":"youtube#searchResult","etag":"\"p4VTdlkQv3HQeTEaXgvLePAydmU/zZlrpbPqtkR3263Ma6JGUZyyuW0\"","id":{"kind":"youtube#video","videoId":"TwB_XIt9zqs"},"snippet":{"publishedAt":"2011-01-09T14:35:56.000Z","channelId":"UCQHzG2gtNfXp4yo6_I46eCw","title":"שלמה ארצי- ארץ חדשה","description":"שלמה ארצי בקליפ לשיר ארץ חדשה, מתוך האלבום חום יולי אוגוסט-1988.","thumbnails":{"default":{"url":"https://i.ytimg.com/vi/TwB_XIt9zqs/default.jpg","width":120,"height":90},"medium":{"url":"https://i.ytimg.com/vi/TwB_XIt9zqs/mqdefault.jpg","width":320,"height":180},"high":{"url":"https://i.ytimg.com/vi/TwB_XIt9zqs/hqdefault.jpg","width":480,"height":360}},"channelTitle":"ShlomoArtziOfficial","liveBroadcastContent":"none"},"_playlist":"xx71wje4akb","_playlistItem":"vc92z7c0zgi"},{"kind":"youtube#searchResult","etag":"\"p4VTdlkQv3HQeTEaXgvLePAydmU/kqo2CTkedt5pDd2stikGymKTgqE\"","id":{"kind":"youtube#video","videoId":"ZwTbFd8kdII"},"snippet":{"publishedAt":"2012-03-29T11:42:17.000Z","channelId":"UC30wWqOnGerlF6ZQgovvQLQ","title":"אריק איינשטיין סע לאט Arik Einstein","description":"לרכישת המארז החדש של אריק איינשטיין: https://confia.co.il/ArikEinstein אריק איינשטיין \"סע לאט\" מתוך האלבום \"סע לאט\" מילים:...","thumbnails":{"default":{"url":"https://i.ytimg.com/vi/ZwTbFd8kdII/default.jpg","width":120,"height":90},"medium":{"url":"https://i.ytimg.com/vi/ZwTbFd8kdII/mqdefault.jpg","width":320,"height":180},"high":{"url":"https://i.ytimg.com/vi/ZwTbFd8kdII/hqdefault.jpg","width":480,"height":360}},"channelTitle":"Arik Einstein Official | אריק איינשטיין הערוץ הרשמי","liveBroadcastContent":"none"},"_playlist":"xx71wje4akb","_playlistItem":"dxwafe67lii"},{"kind":"youtube#searchResult","etag":"\"p4VTdlkQv3HQeTEaXgvLePAydmU/zjq_JHiyrUodkvtOmDq4XH8M6Ms\"","id":{"kind":"youtube#video","videoId":"Ug2Gr-yx-E4"},"snippet":{"publishedAt":"2011-08-13T21:43:04.000Z","channelId":"UCfdEIYkf_ZiN8hrcDHRoftw","title":"Rain King (acoustic version)","description":"I do not own this.","thumbnails":{"default":{"url":"https://i.ytimg.com/vi/Ug2Gr-yx-E4/default.jpg","width":120,"height":90},"medium":{"url":"https://i.ytimg.com/vi/Ug2Gr-yx-E4/mqdefault.jpg","width":320,"height":180},"high":{"url":"https://i.ytimg.com/vi/Ug2Gr-yx-E4/hqdefault.jpg","width":480,"height":360}},"channelTitle":"Brian Altemeier","liveBroadcastContent":"none"},"_playlist":"xx71wje4akb","_playlistItem":"4q4vhkcf2pe"}],"items":[{"kind":"youtube#searchResult","etag":"\"j6xRRd8dTPVVptg711_CSPADRfg/xckbd2CZvQkpgA7vhhJCdT_0-lc\"","id":{"kind":"youtube#video","videoId":"UelDrZ1aFeY"},"snippet":{"publishedAt":"2017-12-15T16:14:30.000Z","channelId":"UC4dqLAF7yT-_DqeYisQ001w","title":"The Beatles - Something","description":"Official site: http://www.thebeatles.com Facebook: https://www.facebook.com/thebeatles/ Instagram: https://www.instagram.com/thebeatles Twitter: ...","thumbnails":{"default":{"url":"https://i.ytimg.com/vi/UelDrZ1aFeY/default.jpg","width":120,"height":90},"medium":{"url":"https://i.ytimg.com/vi/UelDrZ1aFeY/mqdefault.jpg","width":320,"height":180},"high":{"url":"https://i.ytimg.com/vi/UelDrZ1aFeY/hqdefault.jpg","width":480,"height":360}},"channelTitle":"TheBeatlesVEVO","liveBroadcastContent":"none"},"_playlist":"xx71wje4akb","_playlistItem":"x49yawagec"},{"kind":"youtube#searchResult","etag":"\"j6xRRd8dTPVVptg711_CSPADRfg/vyvBSMAfaRfq2mhERyA2FV5Ynhw\"","id":{"kind":"youtube#video","videoId":"KQetemT1sWc"},"snippet":{"publishedAt":"2019-09-26T16:00:11.000Z","channelId":"UC4dqLAF7yT-_DqeYisQ001w","title":"The Beatles - Here Comes The Sun (2019 Mix)","description":"The Beatles “Here Comes The Sun” official video from the Abbey Road album. Out now: http://thebeatles.lnk.to/AbbeyRoad2019 For more information visit ...","thumbnails":{"default":{"url":"https://i.ytimg.com/vi/KQetemT1sWc/default.jpg","width":120,"height":90},"medium":{"url":"https://i.ytimg.com/vi/KQetemT1sWc/mqdefault.jpg","width":320,"height":180},"high":{"url":"https://i.ytimg.com/vi/KQetemT1sWc/hqdefault.jpg","width":480,"height":360}},"channelTitle":"TheBeatlesVEVO","liveBroadcastContent":"none"},"_playlist":"xx71wje4akb","_playlistItem":"msvzskvenbs"}],"show":true,"id":"xx71wje4akd"}